oracle2postgres.py
oracle2postgres-0.1.6.dist-info/LICENSE
oracle2postgres-0.1.6.dist-info/METADATA
oracle2postgres-0.1.6.dist-info/WHEEL
oracle2postgres-0.1.6.dist-info/top_level.txt
oracle2postgres-0.1.6.dist-info/RECORD
